modelpy_abm/__init__.py
modelpy_abm/main.py
modelpy_abm-0.0.4.dist-info/METADATA
modelpy_abm-0.0.4.dist-info/WHEEL
modelpy_abm-0.0.4.dist-info/licenses/LICENSE
modelpy_abm-0.0.4.dist-info/RECORD
