Metadata-Version: 2.3
Name: modelpy-abm
Version: 0.0.4
Summary: Modelpy's Python module.
Project-URL: Homepage, https://github.com/toni-akintola/modelpy-module
Project-URL: Website, https://modelpy.kekoawong.com/
Author-email: Oluwatoni Akintola <oakintol@nd.edu>
License-File: LICENSE
Classifier: License :: OSI Approved :: MIT License
Classifier: Operating System :: OS Independent
Classifier: Programming Language :: Python :: 3
Requires-Python: >=3.10.7
Requires-Dist: networkx==3.3
Requires-Dist: numpy==2.0.0
